KnnRegressionRobi/__init__.py
KnnRegressionRobGin-1.0.0.dist-info/LICENSE
KnnRegressionRobGin-1.0.0.dist-info/METADATA
KnnRegressionRobGin-1.0.0.dist-info/WHEEL
KnnRegressionRobGin-1.0.0.dist-info/top_level.txt
KnnRegressionRobGin-1.0.0.dist-info/RECORD
